vocode/__init__.py
vocode/helpers.py
vocode/logging.py
vocode/meta.py
vocode/streaming/action/abstract_factory.py
vocode/streaming/action/action_utils.py
vocode/streaming/action/base_action.py
vocode/streaming/action/default_factory.py
vocode/streaming/action/dtmf.py
vocode/streaming/action/end_conversation.py
vocode/streaming/action/execute_external_action.py
vocode/streaming/action/external_actions_requester.py
vocode/streaming/action/phone_call_action.py
vocode/streaming/action/record_email.py
vocode/streaming/action/transfer_call.py
vocode/streaming/action/wait.py
vocode/streaming/action/worker.py
vocode/streaming/agent/__init__.py
vocode/streaming/agent/abstract_factory.py
vocode/streaming/agent/anthropic_agent.py
vocode/streaming/agent/anthropic_utils.py
vocode/streaming/agent/base_agent.py
vocode/streaming/agent/chat_gpt_agent.py
vocode/streaming/agent/default_factory.py
vocode/streaming/agent/echo_agent.py
vocode/streaming/agent/goodbye.py
vocode/streaming/agent/gpt4all_agent.py
vocode/streaming/agent/llamacpp_agent.py
vocode/streaming/agent/openai_utils.py
vocode/streaming/agent/phrase_trigger.py
vocode/streaming/agent/restful_user_implemented_agent.py
vocode/streaming/agent/streaming_utils.py
vocode/streaming/agent/token_utils.py
vocode/streaming/agent/vertex_ai_agent.py
vocode/streaming/agent/websocket_user_implemented_agent.py
vocode/streaming/client_backend/conversation.py
vocode/streaming/constants.py
vocode/streaming/input_device/base_input_device.py
vocode/streaming/input_device/file_input_device.py
vocode/streaming/input_device/microphone_input.py
vocode/streaming/models/actions.py
vocode/streaming/models/agent.py
vocode/streaming/models/audio.py
vocode/streaming/models/client_backend.py
vocode/streaming/models/events.py
vocode/streaming/models/message.py
vocode/streaming/models/model.py
vocode/streaming/models/synthesizer.py
vocode/streaming/models/telephony.py
vocode/streaming/models/transcriber.py
vocode/streaming/models/transcript.py
vocode-0.1.112.dist-info/LICENSE
vocode-0.1.112.dist-info/METADATA
vocode-0.1.112.dist-info/WHEEL
vocode-0.1.112.dist-info/RECORD
